klaviyo_api/__init__.py
klaviyo_api/custom_retry.py
klaviyo_api/filter_builder.py
klaviyo_api/wrapper.py
klaviyo_api-21.0.0.dist-info/licenses/LICENSE
openapi_client/__init__.py
openapi_client/api_arg_options.py
openapi_client/api_client.py
openapi_client/api_response.py
openapi_client/configuration.py
openapi_client/exceptions.py
openapi_client/py.typed
openapi_client/rest.py
openapi_client/api/__init__.py
openapi_client/api/accounts_api.py
openapi_client/api/campaigns_api.py
openapi_client/api/catalogs_api.py
openapi_client/api/coupons_api.py
openapi_client/api/custom_objects_api.py
openapi_client/api/data_privacy_api.py
openapi_client/api/events_api.py
openapi_client/api/flows_api.py
openapi_client/api/forms_api.py
openapi_client/api/images_api.py
openapi_client/api/lists_api.py
openapi_client/api/metrics_api.py
openapi_client/api/profiles_api.py
openapi_client/api/reporting_api.py
openapi_client/api/reviews_api.py
openapi_client/api/segments_api.py
openapi_client/api/tags_api.py
openapi_client/api/templates_api.py
openapi_client/api/tracking_settings_api.py
openapi_client/api/web_feeds_api.py
openapi_client/api/webhooks_api.py
openapi_client/models/__init__.py
openapi_client/models/account_enum.py
openapi_client/models/account_response_object_resource.py
openapi_client/models/account_response_object_resource_attributes.py
openapi_client/models/api_job_error_payload.py
openapi_client/models/attribution_enum.py
openapi_client/models/audiences.py
openapi_client/models/audiences_update.py
openapi_client/models/back_in_stock_dynamic_button_border_styles.py
openapi_client/models/back_in_stock_dynamic_button_data.py
openapi_client/models/back_in_stock_dynamic_button_drop_shadow_styles.py
openapi_client/models/back_in_stock_dynamic_button_styles.py
openapi_client/models/back_in_stock_dynamic_button_text_styles.py
openapi_client/models/back_in_stock_subscription_enum.py
openapi_client/models/background_image.py
openapi_client/models/background_image_styles.py
openapi_client/models/banner_styles.py
klaviyo_api-21.0.0.dist-info/METADATA
klaviyo_api-21.0.0.dist-info/WHEEL
klaviyo_api-21.0.0.dist-info/top_level.txt
klaviyo_api-21.0.0.dist-info/RECORD
