Metadata-Version: 2.4
Name: klaviyo-api
Version: 21.0.0
Summary: Klaviyo Python SDK
Home-page: https://github.com/klaviyo/klaviyo-api-python
Author: Klaviyo Developers
Author-email: developers@klaviyo.com
Project-URL: API Docs, https://developers.klaviyo.com/en/reference/api_overview
Classifier: Programming Language :: Python :: 3
Classifier: License :: OSI Approved :: MIT License
Classifier: Operating System :: OS Independent
Requires-Python: >=3.7
License-File: LICENSE
Requires-Dist: python_dateutil>=2.5.3
Requires-Dist: setuptools>=21.0.0
Requires-Dist: urllib3>=1.25.3
Requires-Dist: pydantic>=2
Requires-Dist: aenum>=3.1.11
Dynamic: license-file
